ytools/__init__.py
ytools/__main__.py
ytools/py.typed
ytools3-3.0.1.dist-info/LICENSE
ytools3-3.0.1.dist-info/METADATA
ytools3-3.0.1.dist-info/WHEEL
ytools3-3.0.1.dist-info/entry_points.txt
ytools3-3.0.1.dist-info/top_level.txt
ytools3-3.0.1.dist-info/RECORD
