Metadata-Version: 2.1
Name: ytools3
Version: 3.0.1
Summary: Library for validating `yaml` files against schema and selectively dumping nodes from `yaml` (or `json`) documents in `yaml` or `json` format.
Home-page: https://github.com/domdfcoding/ytools3
Author: Dominic Davis-Foster
Author-email: dominic@davis-foster.co.uk
License: Apache2.0
Project-URL: Documentation, https://ytools3.readthedocs.io
Project-URL: Issue_Tracker, https://github.com/domdfcoding/ytools3/issues
Project-URL: Source_Code, https://github.com/domdfcoding/ytools3
Keywords: yaml,json,transform,xslt,jsonpath,json-path,dump,convert,validate,schema,validation,utility
Platform: Windows
Platform: macOS
Platform: Linux
Classifier: Development Status :: 4 - Beta
Classifier: Intended Audience :: Developers
Classifier: Operating System :: OS Independent
Classifier: Programming Language :: Python
Classifier: Programming Language :: Python :: 3 :: Only
Classifier: Programming Language :: Python :: 3.6
Classifier: Programming Language :: Python :: 3.7
Classifier: Programming Language :: Python :: 3.8
Classifier: Programming Language :: Python :: 3.9
Classifier: Programming Language :: Python :: Implementation :: CPython
Classifier: Programming Language :: Python :: Implementation :: PyPy
Classifier: Topic :: Utilities
Classifier: Typing :: Typed
Requires-Python: >=3.6
Requires-Dist: jsonpath-ng (>=1.5.1)
Requires-Dist: jsonschema (>=3.2.0)
Requires-Dist: PyYAML (>=5.1)
Requires-Dist: strict-rfc3339 (==0.7)
Requires-Dist: typing-extensions
Provides-Extra: all
